{

    "MemoryId":"16Gb_DDR5_7200-6400_B_x8",
    "MemoryType":"DDR5",
    "Is_3ds":false,
    "RefreshMode":1,
    "CmdMode":1,
    "FreqRatio":4,
    "BurstLenth":16,
    "MaxBurstLenth":16,
    "MemArchitect":{
        "NumOfChannels":1,
        "NumOfSubChannelsPerChannel":2,
        "NumOfPseudoChannelsPerSubChannel":1,
        "NumOfPhysicalRanksPerPseudoChannel":2,
        "NumOfLogicalRanksPerPhysicalRank":2
    },
    "Device":{
        "DeviceWidth":8,
        "DataRate":2,
        "NumOfBankGroupsPerDevice":8,
        "NumOfBanksPerBankGroup":4,
        "NumOfColumns":1024,
        "NumOfRows":65536,

        "RAAIMT":32,
        "RAAMMT":3,
        "RAADEC":1
    },
    
    "SpeedBins":{
        "CLK":0.312,
        "Freq":3200,
        "CL":52,
        "nRCD":52,
        "nRP":52,
        "CWL":50,
        "tRCD":16.0,
        "tRP":16.0,
        "tRAS":32.0
    },
    "AcTiming":{
        "tCCD_L_slr": 5.0,
        "tCCD_L_WR_slr": 20.0,
        "tCCD_L_WR2_slr": 10.0,
        "tCCD_L_WTR_slr_part": 10.0,
        "tCCD_M_slr": 5.0,
        "tCCD_M_WR_slr": 20.0,
        "tCCD_M_WTR_slr_part": 10.0,
        "tCCD_S_slr": 8,
        "tCCD_S_WR_slr": 8,
        "tCCD_S_WTR_slr_part": 2.5,
        "tRRD_L_slr": 5.0,
        "tRRD_S_slr": 8,
        "tFAW_slr": 10.0,
        "tRTP_slr": 7.5,
        "tPPD_slr": 2,
        "tWR_slr": 30.0,
        "tCCD_dlr": 0.0,
        "tCCD_WR_dlr": 0.0,
        "tCCD_WTR_dlr_part": 0.0,
        "tRRD_dlr": 0.0,
        "tFAW_dlr": 0.0,
        "tPPD_dlr": 0,
        "tCCD_WR_dpr": 0,
        "tDCAW": 0,
        "nDCAC": 0
    },
    "RefreshAcTiming": {
        "tREFI1": 3900.0,
        "tREFI2": 1950.0,
        "tRFC1_slr": 295.0,
        "tRFC2_slr": 160.0,
        "tRFCsb_slr": 130.0,
        "tRFC1_dlr": 0.0,
        "tRFC1_dpr": 0.0,
        "tRFC2_dlr": 0.0,
        "tRFC2_dpr": 0.0,
        "tRFCsb_dlr": 0.0,
        "tREFSBRD_slr": 30.0,
        "tREFSBRD_dlr": 0.0,
        "tREFABRD_dlr": 0.0
    },
    "DataAcTiming": {
        "tRPRE": 1,
        "tRPST": 0.5,
        "tWPRE": 2,
        "tWPST": 0.5,
        "Read_DQS_Offset": 0
    }
}